estructura_de_computadores/practica1/p1/cal/mux2_1.v
// Multiplexor de 2 entradas de un bit

module mux2_1(output wire out, input wire a, input wire b, input wire s);

  assign out = s ? b : a;

endmodule

estructura_de_computadores/practica1/p1/mux_4_1/mux4_1.v
// Multiplexor de 4 entradas de un bit

module mux4_1(output reg out, input wire a, b, c, d, input wire [1:0] s);

  always @(a or b or c or d or s)
   
   begin

      case (s)              
        2'b00 : out = a;        // caso 00
        2'b01 : out = b;        // caso 01
        2'b10 : out = c;        // caso 10
        2'b11 : out = d;        // caso 11
        default: out = 'bx;
      endcase

    end

endmodule

estructura_de_computadores/practica1/p1/celda_logica/cl.v
// Celda Lógica

module cl(output wire out, input wire a, b, input wire [1:0] s);

  wire salida_and, salida_or, salida_xor, salida_not; // definicion de variables

  and  and1(salida_and, a, b); // realizamos las operaciones
  or   or1(salida_or, a, b);
  xor  xor1(salida_xor, a, b);
  not not1(salida_not, a);

  mux4_1 mi_mux4(out, salida_and, salida_or, salida_xor, salida_not, s);

endmodule

estructura_de_computadores/practica1/p1/full_adder/fa.v
//Full-Adder (operador concatenación '{}')

module fa(output wire cout, sum, input wire a, b, cin);

  assign {cout,sum} = a + b + cin; //operador suma

endmodule

estructura_de_computadores/practica1/p1/cal/cal.v
// Celda aritmético-lógica

module cal(output wire out, c_out, input wire a, b, l, c_in, input wire [1:0] s);

  wire salida_fa, salida_cl; // declaracion de variables

  fa mifa(c_out, salida_fa, a, b, c_in);
  cl micl(salida_cl, a, b, s);           

  mux2_1 mi_mux21(out, salida_fa, salida_cl, l);

endmodule

estructura_de_computadores/practica1/p1/complemento_a_1/compl1.v
// Complementador a 1 de entrada de 4 bits

module compl1(output wire [3:0] Sal, input wire [3:0] Ent, input wire cpl);

  assign Sal = cpl? ~Ent : Ent;

endmodule

estructura_de_computadores/practica1/p1/mux2_4.v

module mux2_4(output wire [3:0] out, input wire [3:0] a, input wire [3:0] b, input wire s);

  assign out = s ? b : a; //oper. condicional de C, sintaxis [condicion ? valor_si_cierta : valor_si_falsa] 

endmodule

estructura_de_computadores/practica1/p1/alu_modificacion.v
// Unidad aritmético-lógica (ALU)
// Compilación:  iverilog alu_tb_v4.v  alu_modificacion.v mux2_4.v  cal/cal.v cal/mux2_1.v  celda_logica/cl.v mux_4_1/mux4_1.v full_adder/fa.v complemento_a_1/compl1.v 

module alu(output wire [3:0] R, output wire zero, carry, sign, input wire[3:0] A, B, input wire [1:0] ALUOp, input wire L);

  wire [3:0] OP1, OP2, OP2_pre;       // Operandos
  wire op1_A, op2_B, cpl;             // Ayuda al calculo de operandos
  wire c_in0, c_out0, c_out1, c_out2; // Cin/cout 's


  // Definición de las funciones lógicas de op1_A, op2_b, cpl y c_in0
  assign op1_A  = ~ALUOp[1] | L;
  assign op2_B  = ~ALUOp[1] | ~ALUOp[0];
  assign cpl    = ~L & ~ALUOp[0] | ~L & ALUOp[1];
  assign c_in0  = ALUOp[1] | ~ALUOp[0];


  mux2_4 mimux2_4_1(OP1, 4'b0000, A, op1_A); // Cálculo de OP1
  mux2_4 mimux2_4_2(OP2_pre, A, B, op2_B);
  compl1 compl1_B(OP2, OP2_pre, cpl);        // Cálculo de OP2


  // Instanciación de las 4 celdas aritmético-lógicas
  cal cal0(R[0], c_out0, OP1[0], OP2[0], L, c_in0, ALUOp); 
  cal cal1(R[1], c_out1, OP1[1], OP2[1], L, c_out0, ALUOp);
  cal cal2(R[2], c_out2, OP1[2], OP2[2], L, c_out1, ALUOp);
  cal cal3(R[3], carry,  OP1[3], OP2[3], L, c_out2, ALUOp);

  // Otras señales
  assign zero = ~R[0] & ~R[1] & ~R[2] & ~R[3];
  assign sign = R[3];

endmodule

estructura_de_computadores/practica1/p1/alu_tb_v4.v
// Testbench para modulo alu, cambiando orden de operaciones aritméticas: 00 A-B; 01 A+B; 10 Cpl2(B); 11 Cpl2(A)
`timescale 1 ns / 10 ps //Directiva que fija la unidad de tiempo de simulación y la precision de la unidad
module alu_tb;
//declaracion de señales
reg [1:0] t_Op;
reg t_L;
reg [3:0] t_A, t_B;
wire [3:0] t_R;
wire t_z, t_c, t_s;
integer errores;
//instancia del modulo a testear
alu mat(t_R, t_z, t_c, t_s, t_A, t_B, t_Op, t_L);

initial
begin
  $dumpfile("alu.vcd");
  $dumpvars;
  errores = 0;
  t_L = 1'b0;
  repeat(2)
	begin
	t_Op = 2'b0;
	repeat(4)
		begin
		  t_A = 4'b0;
		  repeat(16) 
		  begin
			t_B = 4'b0;
			repeat(16) 
			begin
				# 2 check;
				t_B = t_B + 1;
			end
			t_A = t_A + 1;
		  end
		  t_Op = t_Op + 1;
		end
		t_L = t_L + 1;
	end
	$display("Encontradas %d operaciones erroneas", errores);
  //fin simulacion
  $finish;
end

// Tarea para hacer la comprobación automática de resultados
task check;
reg [4:0] result;
reg flag_zero, flag_carry, flag_sign;
begin
	// Si las operaciones son lógicas
	if (t_L)
	begin
		case (t_Op)
			2'b00: result[3:0] = t_A & t_B;
			2'b01: result[3:0] = t_A | t_B;
			2'b10: result[3:0] = t_A ^ t_B;
			2'b11: result[3:0] = ~t_A;
			default: $display("ERROR. Valor no esperado para t_Op: %b", t_Op);
		endcase
		flag_carry = 1'bx;
		flag_sign = 1'bx;
	end
	else
	begin
		case (t_Op)
			2'b00: result = t_A + ((t_B ^4'b1111) + 1);
			2'b01: result = t_A + t_B;
			2'b10: result = (t_B ^4'b1111) + 4'b0001;
			2'b11: result = (t_A ^4'b1111) + 4'b0001;
			default: $display("ERROR. Valor no esperado para t_Op: %b", t_Op);
		endcase
		flag_carry = result[4];
		flag_sign = result[3];
		if (flag_sign !== t_s || flag_carry !== t_c)
		begin
			errores = errores + 1;
			$display("ERROR con operación L=%b, OP=%b A=%b B=%b", t_L, t_Op, t_A, t_B);
			if (flag_sign !== t_s)
				$display("ERROR. Flag de signo esperado %b, obtenido %b", flag_sign, t_s);
			if (flag_carry !== t_c)
				$display("\tFlag de acarreo esperado %b, obtenido %b", flag_carry, t_c);
		end
	end
	flag_zero = ~| result[3:0];
	if (result[3:0] !== t_R || flag_zero !== t_z)
	begin
		errores = errores + 1;
		$display("ERROR con operación L=%b, OP=%b A=%b B=%b", t_L, t_Op, t_A, t_B);
		if (result[3:0] !== t_R)
			$display("\tResultado esperado %b, obtenido %b", result[3:0], t_R);
		if (flag_zero !== t_z)
			$display("\tFlag de cero esperado %b, obtenido %b", flag_zero, t_z);
	end
end
endtask
endmodule

estructura_de_computadores/practica1/p1/alu.vcd
$date
	Wed Nov 11 15:15:51 2020
$end
$version
	Icarus Verilog
$end
$timescale
	10ps
$end
$scope module alu_tb $end
$var wire 4 ! t_R [3:0] $end
$var wire 1 " t_c $end
$var wire 1 # t_s $end
$var wire 1 $ t_z $end
$var integer 32 % errores [31:0] $end
$var reg 4 & t_A [3:0] $end
$var reg 4 ' t_B [3:0] $end
$var reg 1 ( t_L $end
$var reg 2 ) t_Op [1:0] $end
$scope module mat $end
$var wire 4 * A [3:0] $end
$var wire 2 + ALUOp [1:0] $end
$var wire 4 , B [3:0] $end
$var wire 1 - L $end
$var wire 4 . OP1 [3:0] $end
$var wire 4 / OP2 [3:0] $end
$var wire 4 0 OP2_pre [3:0] $end
$var wire 4 1 R [3:0] $end
$var wire 1 2 c_in0 $end
$var wire 1 3 c_out0 $end
$var wire 1 4 c_out1 $end
$var wire 1 5 c_out2 $end
$var wire 1 " carry $end
$var wire 1 6 cpl $end
$var wire 1 7 op1_A $end
$var wire 1 8 op2_B $end
$var wire 1 # sign $end
$var wire 1 $ zero $end
$scope module mimux2_4_1 $end
$var wire 4 9 a [3:0] $end
$var wire 4 : b [3:0] $end
$var wire 4 ; out [3:0] $end
$var wire 1 7 s $end
$upscope $end
$scope module mimux2_4_2 $end
$var wire 4 < a [3:0] $end
$var wire 4 = b [3:0] $end
$var wire 4 > out [3:0] $end
$var wire 1 8 s $end
$upscope $end
$scope module compl1_B $end
$var wire 4 ? Ent [3:0] $end
$var wire 4 @ Sal [3:0] $end
$var wire 1 6 cpl $end
$upscope $end
$scope module cal0 $end
$var wire 1 A a $end
$var wire 1 B b $end
$var wire 1 2 c_in $end
$var wire 1 3 c_out $end
$var wire 1 - l $end
$var wire 1 C out $end
$var wire 2 D s [1:0] $end
$var wire 1 E salida_cl $end
$var wire 1 F salida_fa $end
$scope module mifa $end
$var wire 1 A a $end
$var wire 1 B b $end
$var wire 1 2 cin $end
$var wire 1 3 cout $end
$var wire 1 F sum $end
$upscope $end
$scope module micl $end
$var wire 1 A a $end
$var wire 1 B b $end
$var wire 1 E out $end
$var wire 2 G s [1:0] $end
$var wire 1 H salida_and $end
$var wire 1 I salida_not $end
$var wire 1 J salida_or $end
$var wire 1 K salida_xor $end
$scope module mi_mux4 $end
$var wire 1 H a $end
$var wire 1 J b $end
$var wire 1 K c $end
$var wire 1 I d $end
$var wire 2 L s [1:0] $end
$var reg 1 M out $end
$upscope $end
$upscope $end
$scope module mi_mux21 $end
$var wire 1 F a $end
$var wire 1 E b $end
$var wire 1 C out $end
$var wire 1 - s $end
$upscope $end
$upscope $end
$scope module cal1 $end
$var wire 1 N a $end
$var wire 1 O b $end
$var wire 1 3 c_in $end
$var wire 1 4 c_out $end
$var wire 1 - l $end
$var wire 1 P out $end
$var wire 2 Q s [1:0] $end
$var wire 1 R salida_cl $end
$var wire 1 S salida_fa $end
$scope module mifa $end
$var wire 1 N a $end
$var wire 1 O b $end
$var wire 1 3 cin $end
$var wire 1 4 cout $end
$var wire 1 S sum $end
$upscope $end
$scope module micl $end
$var wire 1 N a $end
$var wire 1 O b $end
$var wire 1 R out $end
$var wire 2 T s [1:0] $end
$var wire 1 U salida_and $end
$var wire 1 V salida_not $end
$var wire 1 W salida_or $end
$var wire 1 X salida_xor $end
$scope module mi_mux4 $end
$var wire 1 U a $end
$var wire 1 W b $end
$var wire 1 X c $end
$var wire 1 V d $end
$var wire 2 Y s [1:0] $end
$var reg 1 Z out $end
$upscope $end
$upscope $end
$scope module mi_mux21 $end
$var wire 1 S a $end
$var wire 1 R b $end
$var wire 1 P out $end
$var wire 1 - s $end
$upscope $end
$upscope $end
$scope module cal2 $end
$var wire 1 [ a $end
$var wire 1 \ b $end
$var wire 1 4 c_in $end
$var wire 1 5 c_out $end
$var wire 1 - l $end
$var wire 1 ] out $end
$var wire 2 ^ s [1:0] $end
$var wire 1 _ salida_cl $end
$var wire 1 ` salida_fa $end
$scope module mifa $end
$var wire 1 [ a $end
$var wire 1 \ b $end
$var wire 1 4 cin $end
$var wire 1 5 cout $end
$var wire 1 ` sum $end
$upscope $end
$scope module micl $end
$var wire 1 [ a $end
$var wire 1 \ b $end
$var wire 1 _ out $end
$var wire 2 a s [1:0] $end
$var wire 1 b salida_and $end
$var wire 1 c salida_not $end
$var wire 1 d salida_or $end
$var wire 1 e salida_xor $end
$scope module mi_mux4 $end
$var wire 1 b a $end
$var wire 1 d b $end
$var wire 1 e c $end
$var wire 1 c d $end
$var wire 2 f s [1:0] $end
$var reg 1 g out $end
$upscope $end
$upscope $end
$scope module mi_mux21 $end
$var wire 1 ` a $end
$var wire 1 _ b $end
$var wire 1 ] out $end
$var wire 1 - s $end
$upscope $end
$upscope $end
$scope module cal3 $end
$var wire 1 h a $end
$var wire 1 i b $end
$var wire 1 5 c_in $end
$var wire 1 " c_out $end
$var wire 1 - l $end
$var wire 1 j out $end
$var wire 2 k s [1:0] $end
$var wire 1 l salida_cl $end
$var wire 1 m salida_fa $end
$scope module mifa $end
$var wire 1 h a $end
$var wire 1 i b $end
$var wire 1 5 cin $end
$var wire 1 " cout $end
$var wire 1 m sum $end
$upscope $end
$scope module micl $end
$var wire 1 h a $end
$var wire 1 i b $end
$var wire 1 l out $end
$var wire 2 n s [1:0] $end
$var wire 1 o salida_and $end
$var wire 1 p salida_not $end
$var wire 1 q salida_or $end
$var wire 1 r salida_xor $end
$scope module mi_mux4 $end
$var wire 1 o a $end
$var wire 1 q b $end
$var wire 1 r c $end
$var wire 1 p d $end
$var wire 2 s s [1:0] $end
$var reg 1 t out $end
$upscope $end
$upscope $end
$scope module mi_mux21 $end
$var wire 1 m a $end
$var wire 1 l b $end
$var wire 1 j out $end
$var wire 1 - s $end
$upscope $end
$upscope $end
$upscope $end
$scope task check $end
$var reg 1 u flag_carry $end
$var reg 1 v flag_sign $end
$var reg 1 w flag_zero $end
$var reg 5 x result [4:0] $end
$upscope $end
$upscope $end
$enddefinitions $end
#0
$dumpvars
bx x
xw
xv
xu
0t
b0 s
1r
1q
1p
0o
b0 n
0m
0l
b0 k
0j
1i
0h
0g
b0 f
1e
1d
1c
0b
b0 a
0`
0_
b0 ^
0]
1\
0[
0Z
b0 Y
1X
1W
1V
0U
b0 T
0S
0R
b0 Q
0P
1O
0N
0M
b0 L
1K
1J
1I
0H
b0 G
0F
0E
b0 D
0C
1B
0A
b1111 @
b0 ?
b0 >
b0 =
b0 <
b0 ;
b0 :
b0 9
18
17
16
15
14
13
12
b0 1
b0 0
b1111 /
b0 .
0-
b0 ,
b0 +
b0 *
b0 )
0(
b0 '
b0 &
b0 %
1$
0#
1"
b0 !
$end
#200
0$
1#
1j
1]
1m
0"
1P
1`
05
1C
b1111 !
b1111 1
1S
04
1F
03
0J
0K
0B
b1110 /
b1110 @
b1 0
b1 >
b1 ?
b1 '
b1 ,
b1 =
1w
0v
1u
b10000 x
#400
0C
b1110 !
b1110 1
0W
0X
0F
13
1J
1K
0O
1B
b1101 /
b1101 @
b10 0
b10 >
b10 ?
b10 '
b10 ,
b10 =
0w
1v
0u
b1111 x
#600
0P
1C
b1101 !
b1101 1
0S
1F
03
0J
0K
0B
b1100 /
b1100 @
b11 0
b11 >
b11 ?
b11 '
b11 ,
b11 =
b1110 x
#800
1]
0C
b1100 !
b1100 1
14
1`
0d
0e
1W
1X
0F
13
1J
1K
0\
1O
1B
b1011 /
b1011 @
b100 0
b100 >
b100 ?
b100 '
b100 ,
b100 =
b1101 x
#1000
0]
1P
0`
1C
b1011 !
b1011 1
1S
04
1F
03
0J
0K
0B
b1010 /
b1010 @
b101 0
b101 >
b101 ?
b101 '
b101 ,
b101 =
b1100 x
#1200
0C
b1010 !
b1010 1
0W
0X
0F
13
1J
1K
0O
1B
b1001 /
b1001 @
b110 0
b110 >
b110 ?
b110 '
b110 ,
b110 =
b1011 x
#1400
0P
1C
b1001 !
b1001 1
0S
1F
03
0J
0K
0B
b1000 /
b1000 @
b111 0
b111 >
b111 ?
b111 '
b111 ,
b111 =
b1010 x
#1600
1#
15
1j
0]
0C
b1000 !
b1000 1
14
1m
0q
0r
0`
1d
1e
1W
1X
0F
13
1J
1K
0i
1\
1O
1B
b111 /
b111 @
b1000 0
b1000 >
b1000 ?
b1000 '
b1000 ,
b1000 =
b1001 x
#1800
0#
0j
1]
0m
1P
1`
05
1C
b111 !
b111 1
1S
04
1F
03
0J
0K
0B
b110 /
b110 @
b1001 0
b1001 >
b1001 ?
b1001 '
b1001 ,
b1001 =
b1000 x
#2000
0C
b110 !
b110 1
0W
0X
0F
13
1J
1K
0O
1B
b101 /
b101 @
b1010 0
b1010 >
b1010 ?
b1010 '
b1010 ,
b1010 =
0v
b111 x
#2200
0P
1C
b101 !
b101 1
0S
1F
03
0J
0K
0B
b100 /
b100 @
b1011 0
b1011 >
b1011 ?
b1011 '
b1011 ,
b1011 =
b110 x
#2400
0$
1]
0C
b100 !
b100 1
14
1`
0d
0e
1W
1X
0F
13
1J
1K
0\
1O
1B
b11 /
b11 @
b1100 0
b1100 >
b1100 ?
b1100 '
b1100 ,
b1100 =
b101 x
#2600
0]
1P
0`
1C
b11 !
b11 1
1S
04
1F
03
0J
0K
0B
b10 /
b10 @
b1101 0
b1101 >
b1101 ?
b1101 '
b1101 ,
b1101 =
b100 x
#2800
0C
b10 !
b10 1
0W
0X
0F
13
1J
1K
0O
1B
b1 /
b1 @
b1110 0
b1110 >
b1110 ?
b1110 '
b1110 ,
b1110 =
b11 x
#3000
0P
1C
b1 !
b1 1
0S
1F
03
0J
0K
0B
b0 /
b0 @
b1111 0
b1111 >
b1111 ?
b1111 '
b1111 ,
b1111 =
b10 x
#3200
0#
1"
0j
15
1M
1E
0m
1q
1r
1d
1e
14
1W
1X
1H
1C
b1 !
b1 1
1i
1\
1O
1B
1F
13
1J
0K
0I
b1111 /
b1111 @
1A
b1 .
b1 ;
b0 0
b0 >
b0 ?
b1 &
b1 *
b1 :
b1 <
b0 '
b0 ,
b0 =
b1 x
#3400
1$
0C
b0 !
b0 1
0M
0E
0F
0H
1K
0B
b1110 /
b1110 @
b1 0
b1 >
b1 ?
b1 '
b1 ,
b1 =
1u
b10001 x
#3600
0$
1#
1j
1]
1m
0"
1P
1`
05
1C
b1111 !
b1111 1
1M
1E
1S
04
0W
0X
1F
1H
0K
0O
1B
b1101 /
b1101 @
b10 0
b10 >
b10 ?
b10 '
b10 ,
b10 =
1w
b10000 x
#3800
0C
b1110 !
b1110 1
0M
0E
0F
0H
1K
0B
b1100 /
b1100 @
b11 0
b11 >
b11 ?
b11 '
b11 ,
b11 =
0w
1v
0u
b1111 x
#4000
0P
1C
b1101 !
b1101 1
1M
1E
0d
0e
0S
14
1W
1X
1F
1H
0K
0\
1O
1B
b1011 /
b1011 @
b100 0
b100 >
b100 ?
b100 '
b100 ,
b100 =
b1110 x
#4200
0C
b1100 !
b1100 1
0M
0E
0F
0H
1K
0B
b1010 /
b1010 @
b101 0
b101 >
b101 ?
b101 '
b101 ,
b101 =
b1101 x
#4400
0]
1P
0`
1C
b1011 !
b1011 1
1M
1E
1S
04
0W
0X
1F
1H
0K
0O
1B
b1001 /
b1001 @
b110 0
b110 >
b110 ?
b110 '
b110 ,
b110 =
b1100 x
#4600
0C
b1010 !
b1010 1
0M
0E
0F
0H
1K
0B
b1000 /
b1000 @
b111 0
b111 >
b111 ?
b111 '
b111 ,
b111 =
b1011 x
#4800
1#
1j
0P
15
1C
b1001 !
b1001 1
1M
1E
1m
0q
0r
1d
1e
0S
14
1W
1X
1F
1H
0K
0i
1\
1O
1B
b111 /
b111 @
b1000 0
b1000 >
b1000 ?
b1000 '
b1000 ,
b1000 =
b1010 x
#5000
0C
b1000 !
b1000 1
0M
0E
0F
0H
1K
0B
b110 /
b110 @
b1001 0
b1001 >
b1001 ?
b1001 '
b1001 ,
b1001 =
b1001 x
#5200
0#
0j
1]
0m
1P
1`
05
1C
b111 !
b111 1
1M
1E
1S
04
0W
0X
1F
1H
0K
0O
1B
b101 /
b101 @
b1010 0
b1010 >
b1010 ?
b1010 '
b1010 ,
b1010 =
b1000 x
#5400
0C
b110 !
b110 1
0M
0E
0F
0H
1K
0B
b100 /
b100 @
b1011 0
b1011 >
b1011 ?
b1011 '
b1011 ,
b1011 =
0v
b111 x
#5600
0P
1C
b101 !
b101 1
1M
1E
0d
0e
0S
14
1W
1X
1F
1H
0K
0\
1O
1B
b11 /
b11 @
b1100 0
b1100 >
b1100 ?
b1100 '
b1100 ,
b1100 =
b110 x
#5800
0C
b100 !
b100 1
0M
0E
0F
0H
1K
0B
b10 /
b10 @
b1101 0
b1101 >
b1101 ?
b1101 '
b1101 ,
b1101 =
b101 x
#6000
0]
1P
0`
1C
b11 !
b11 1
1M
1E
1S
04
0W
0X
1F
1H
0K
0O
1B
b1 /
b1 @
b1110 0
b1110 >
b1110 ?
b1110 '
b1110 ,
b1110 =
b100 x
#6200
0C
b10 !
b10 1
0M
0E
0F
0H
1K
0B
b0 /
b0 @
b1111 0
b1111 >
b1111 ?
b1111 '
b1111 ,
b1111 =
b11 x
#6400
0#
1"
0j
15
1Z
1R
0m
1q
1r
1d
1e
14
1U
0C
b10 !
b10 1
1i
1\
1O
1B
1W
0X
0V
0F
13
1J
1K
1I
b1111 /
b1111 @
1N
0A
b10 .
b10 ;
b0 0
b0 >
b0 ?
b10 &
b10 *
b10 :
b10 <
b0 '
b0 ,
b0 =
b10 x
#6600
0P
1C
b1 !
b1 1
0S
1F
03
0J
0K
0B
b1110 /
b1110 @
b1 0
b1 >
b1 ?
b1 '
b1 ,
b1 =
1u
b10010 x
#6800
1$
0Z
0R
0C
b0 !
b0 1
0U
1X
0F
13
1J
1K
0O
1B
b1101 /
b1101 @
b10 0
b10 >
b10 ?
b10 '
b10 ,
b10 =
b10001 x
#7000
0$
1#
1j
1]
1m
0"
1P
1`
05
1C
b1111 !
b1111 1
1S
04
1F
03
0J
0K
0B
b1100 /
b1100 @
b11 0
b11 >
b11 ?
b11 '
b11 ,
b11 =
1w
b10000 x
#7200
1Z
1R
0C
b1110 !
b1110 1
0d
0e
14
1U
0X
0F
13
1J
1K
0\
1O
1B
b1011 /
b1011 @
b100 0
b100 >
b100 ?
b100 '
b100 ,
b100 =
0w
1v
0u
b1111 x
#7400
0P
1C
b1101 !
b1101 1
0S
1F
03
0J
0K
0B
b1010 /
b1010 @
b101 0
b101 >
b101 ?
b101 '
b101 ,
b101 =
b1110 x
#7600
0Z
0R
0C
b1100 !
b1100 1
0U
1X
0F
13
1J
1K
0O
1B
b1001 /
b1001 @
b110 0
b110 >
b110 ?
b110 '
b110 ,
b110 =
b1101 x
#7800
0]
1P
0`
1C
b1011 !
b1011 1
1S
04
1F
03
0J
0K
0B
b1000 /
b1000 @
b111 0
b111 >
b111 ?
b111 '
b111 ,
b111 =
b1100 x
#8000
1#
1j
15
1Z
1R
0C
b1010 !
b1010 1
1m
0q
0r
1d
1e
14
1U
0X
0F
13
1J
1K
0i
1\
1O
1B
b111 /
b111 @
b1000 0
b1000 >
b1000 ?
b1000 '
b1000 ,
b1000 =
b1011 x
#8200
0P
1C
b1001 !
b1001 1
0S
1F
03
0J
0K
0B
b110 /
b110 @
b1001 0
b1001 >
b1001 ?
b1001 '
b1001 ,
b1001 =
b1010 x
#8400
0Z
0R
0C
b1000 !
b1000 1
0U
1X
0F
13
1J
1K
0O
1B
b101 /
b101 @
b1010 0
b1010 >
b1010 ?
b1010 '
b1010 ,
b1010 =
b1001 x
#8600
0#
0j
1]
0m
1P
1`
05
1C
b111 !
b111 1
1S
04
1F
03
0J
0K
0B
b100 /
b100 @
b1011 0
b1011 >
b1011 ?
b1011 '
b1011 ,
b1011 =
b1000 x
#8800
1Z
1R
0C
b110 !
b110 1
0d
0e
14
1U
0X
0F
13
1J
1K
0\
1O
1B
b11 /
b11 @
b1100 0
b1100 >
b1100 ?
b1100 '
b1100 ,
b1100 =
0v
b111 x
#9000
0P
1C
b101 !
b101 1
0S
1F
03
0J
0K
0B
b10 /
b10 @
b1101 0
b1101 >
b1101 ?
b1101 '
b1101 ,
b1101 =
b110 x
#9200
0Z
0R
0C
b100 !
b100 1
0U
1X
0F
13
1J
1K
0O
1B
b1 /
b1 @
b1110 0
b1110 >
b1110 ?
b1110 '
b1110 ,
b1110 =
b101 x
#9400
0]
1P
0`
1C
b11 !
b11 1
1S
04
1F
03
0J
0K
0B
b0 /
b0 @
b1111 0
b1111 >
b1111 ?
b1111 '
b1111 ,
b1111 =
b100 x
#9600
0#
1"
0j
1Z
1R
1M
1E
15
0m
1q
1r
1d
1e
1U
0X
1H
1C
b11 !
b11 1
14
1i
1\
1O
1B
1F
13
1J
0K
0I
b1111 /
b1111 @
1A
b11 .
b11 ;
b0 0
b0 >
b0 ?
b11 &
b11 *
b11 :
b11 <
b0 '
b0 ,
b0 =
b11 x
#9800
0C
b10 !
b10 1
0M
0E
0F
0H
1K
0B
b1110 /
b1110 @
b1 0
b1 >
b1 ?
b1 '
b1 ,
b1 =
1u
b10011 x
#10000
0P
0Z
0R
1C
b1 !
b1 1
1M
1E
0S
0U
1X
1F
1H
0K
0O
1B
b1101 /
b1101 @
b10 0
b10 >
b10 ?
b10 '
b10 ,
b10 =
b10010 x
#10200
1$
0C
b0 !
b0 1
0M
0E
0F
0H
1K
0B
b1100 /
b1100 @
b11 0
b11 >
b11 ?
b11 '
b11 ,
b11 =
b10001 x
#10400
0$
1#
1j
1]
1m
0"
1P
1Z
1R
1C
b1111 !
b1111 1
1M
1E
1`
05
0d
0e
1S
1U
0X
1F
1H
0K
0\
1O
1B
b1011 /
b1011 @
b100 0
b100 >
b100 ?
b100 '
b100 ,
b100 =
1w
b10000 x
#10600
0C
b1110 !
b1110 1
0M
0E
0F
0H
1K
0B
b1010 /
b1010 @
b101 0
b101 >
b101 ?
b101 '
b101 ,
b101 =
0w
1v
0u
b1111 x
#10800
0P
0Z
0R
1C
b1101 !
b1101 1
1M
1E
0S
0U
1X
1F
1H
0K
0O
1B
b1001 /
b1001 @
b110 0
b110 >
b110 ?
b110 '
b110 ,
b110 =
b1110 x
#11000
0C
b1100 !
b1100 1
0M
0E
0F
0H
1K
0B
b1000 /
b1000 @
b111 0
b111 >
b111 ?
b111 '
b111 ,
b111 =
b1101 x
#11200
0]
1P
1Z
1R
1C
b1011 !
b1011 1
1M
1E
0q
0r
0`
15
1d
1e
1S
1U
0X
1F
1H
0K
0i
1\
1O
1B
b111 /
b111 @
b1000 0
b1000 >
b1000 ?
b1000 '
b1000 ,
b1000 =
b1100 x
#11400
0C
b1010 !
b1010 1
0M
0E
0F
0H
1K
0B
b110 /
b110 @
b1001 0
b1001 >
b1001 ?
b1001 '
b1001 ,
b1001 =
b1011 x
#11600
0P
0Z
0R
1C
b1001 !
b1001 1
1M
1E
0S
0U
1X
1F
1H
0K
0O
1B
b101 /
b101 @
b1010 0
b1010 >
b1010 ?
b1010 '
b1010 ,
b1010 =
b1010 x
#11800
0C
b1000 !
b1000 1
0M
0E
0F
0H
1K
0B
b100 /
b100 @
b1011 0
b1011 >
b1011 ?
b1011 '
b1011 ,
b1011 =
b1001 x
#12000
0#
0j
1]
0m
1P
1Z
1R
1C
b111 !
b111 1
1M
1E
1`
05
0d
0e
1S
1U
0X
1F
1H
0K
0\
1O
1B
b11 /
b11 @
b1100 0
b1100 >
b1100 ?
b1100 '
b1100 ,
b1100 =
b1000 x
#12200
0C
b110 !
b110 1
0M
0E
0F
0H
1K
0B
b10 /
b10 @
b1101 0
b1101 >
b1101 ?
b1101 '
b1101 ,
b1101 =
0v
b111 x
#12400
0P
0Z
0R
1C
b101 !
b101 1
1M
1E
0S
0U
1X
1F
1H
0K
0O
1B
b1 /
b1 @
b1110 0
b1110 >
b1110 ?
b1110 '
b1110 ,
b1110 =
b110 x
#12600
0C
b100 !
b100 1
0M
0E
0F
0H
1K
0B
b0 /
b0 @
b1111 0
b1111 >
b1111 ?
b1111 '
b1111 ,
b1111 =
b101 x
#12800
1]
1"
1g
1_
1q
1r
1`
15
1b
0C
b100 !
b100 1
1i
1\
1O
1B
1d
0e
0c
14
1W
1X
1V
0F
13
1J
1K
1I
b1111 /
b1111 @
1[
0N
0A
b100 .
b100 ;
b0 0
b0 >
b0 ?
b100 &
b100 *
b100 :
b100 <
b0 '
b0 ,
b0 =
b100 x
#13000
0]
1P
0`
1C
b11 !
b11 1
1S
04
1F
03
0J
0K
0B
b1110 /
b1110 @
b1 0
b1 >
b1 ?
b1 '
b1 ,
b1 =
1u
b10100 x
#13200
0C
b10 !
b10 1
0W
0X
0F
13
1J
1K
0O
1B
b1101 /
b1101 @
b10 0
b10 >
b10 ?
b10 '
b10 ,
b10 =
b10011 x
#13400
0P
1C
b1 !
b1 1
0S
1F
03
0J
0K
0B
b1100 /
b1100 @
b11 0
b11 >
b11 ?
b11 '
b11 ,
b11 =
b10010 x
#13600
1$
0#
0j
0]
0m
1"
0g
0_
0C
b0 !
b0 1
14
0`
15
0b
1e
1W
1X
0F
13
1J
1K
0\
1O
1B
b1011 /
b1011 @
b100 0
b100 >
b100 ?
b100 '
b100 ,
b100 =
b10001 x
#13800
0$
1#
1j
1]
1m
0"
1P
1`
05
1C
b1111 !
b1111 1
1S
04
1F
03
0J
0K
0B
b1010 /
b1010 @
b101 0
b101 >
b101 ?
b101 '
b101 ,
b101 =
1w
b10000 x
#14000
0C
b1110 !
b1110 1
0W
0X
0F
13
1J
1K
0O
1B
b1001 /
b1001 @
b110 0
b110 >
b110 ?
b110 '
b110 ,
b110 =
0w
1v
0u
b1111 x
#14200
0P
1C
b1101 !
b1101 1
0S
1F
03
0J
0K
0B
b1000 /
b1000 @
b111 0
b111 >
b111 ?
b111 '
b111 ,
b111 =
b1110 x
#14400
1]
1g
1_
0C
b1100 !
b1100 1
14
0q
0r
1`
15
1b
0e
1W
1X
0F
13
1J
1K
0i
1\
1O
1B
b111 /
b111 @
b1000 0
b1000 >
b1000 ?
b1000 '
b1000 ,
b1000 =
b1101 x
#14600
0]
1P
0`
1C
b1011 !
b1011 1
1S
04
1F
03
0J
0K
0B
b110 /
b110 @
b1001 0
b1001 >
b1001 ?
b1001 '
b1001 ,
b1001 =
b1100 x
#14800
0C
b1010 !
b1010 1
0W
0X
0F
13
1J
1K
0O
1B
b101 /
b101 @
b1010 0
b1010 >
b1010 ?
b1010 '
b1010 ,
b1010 =
b1011 x
#15000
0P
1C
b1001 !
b1001 1
0S
1F
03
0J
0K
0B
b100 /
b100 @
b1011 0
b1011 >
b1011 ?
b1011 '
b1011 ,
b1011 =
b1010 x
#15200
1#
1j
0]
1m
0g
0_
0C
b1000 !
b1000 1
14
0`
15
0b
1e
1W
1X
0F
13
1J
1K
0\
1O
1B
b11 /
b11 @
b1100 0
b1100 >
b1100 ?
b1100 '
b1100 ,
b1100 =
b1001 x
#15400
0#
0j
1]
0m
1P
1`
05
1C
b111 !
b111 1
1S
04
1F
03
0J
0K
0B
b10 /
b10 @
b1101 0
b1101 >
b1101 ?
b1101 '
b1101 ,
b1101 =
b1000 x
#15600
0C
b110 !
b110 1
0W
0X
0F
13
1J
1K
0O
1B
b1 /
b1 @
b1110 0
b1110 >
b1110 ?
b1110 '
b1110 ,
b1110 =
0v
b111 x
